<?xml version="1.0" encoding="UTF-8" standalone="yes"?>
<ForumType>
    <registeredUsers>
        <username>sepetnit</username>
        <e-mail>fff@ggg</e-mail>
        <password>uyjzb3Bz</password>
        <lastName>sepet</lastName>
        <firstName>vit</firstName>
        <numOfPostedMessages>3</numOfPostedMessages>
    </registeredUsers>
    <registeredUsers>
        <username>yakir</username>
        <e-mail>dahany@bgu.ac.il</e-mail>
        <password>1234</password>
        <lastName>Dahan</lastName>
        <firstName>Yakir</firstName>
        <numOfPostedMessages>1</numOfPostedMessages>
    </registeredUsers>
    <forumSubjects>
        <name>abc</name>
        <description>def</description>
        <numOfMessages>0</numOfMessages>
        <subjectID>0</subjectID>
        <subThreads>
            <startMessage>
                <messageID>0</messageID>
                <author>
                    <username>sepetnit</username>
                    <e-mail>fff@ggg</e-mail>
                    <password>uyjzb3Bz</password>
                    <lastName>sepet</lastName>
                    <firstName>vit</firstName>
                    <numOfPostedMessages>1</numOfPostedMessages>
                </author>
                <title>hello</title>
                <content>world</content>
                <date>2010-03-15+02:00</date>
                <time>11:53:29.703+02:00</time>
            </startMessage>
            <lastMessage>
                <messageID>0</messageID>
                <author>
                    <username>sepetnit</username>
                    <e-mail>fff@ggg</e-mail>
                    <password>uyjzb3Bz</password>
                    <lastName>sepet</lastName>
                    <firstName>vit</firstName>
                    <numOfPostedMessages>1</numOfPostedMessages>
                </author>
                <title>hello</title>
                <content>world</content>
                <date>2010-03-15+02:00</date>
                <time>11:53:29.703+02:00</time>
            </lastMessage>
            <numOfViews>0</numOfViews>
            <numOfResponses>0</numOfResponses>
        </subThreads>
        <subThreads>
            <startMessage>
                <messageID>1</messageID>
                <author>
                    <username>sepetnit</username>
                    <e-mail>fff@ggg</e-mail>
                    <password>uyjzb3Bz</password>
                    <lastName>sepet</lastName>
                    <firstName>vit</firstName>
                    <numOfPostedMessages>2</numOfPostedMessages>
                </author>
                <title>sepetnit</title>
                <content>hello</content>
                <date>2010-03-15+02:00</date>
                <time>11:54:11.484+02:00</time>
            </startMessage>
            <lastMessage>
                <messageID>1</messageID>
                <author>
                    <username>sepetnit</username>
                    <e-mail>fff@ggg</e-mail>
                    <password>uyjzb3Bz</password>
                    <lastName>sepet</lastName>
                    <firstName>vit</firstName>
                    <numOfPostedMessages>2</numOfPostedMessages>
                </author>
                <title>sepetnit</title>
                <content>hello</content>
                <date>2010-03-15+02:00</date>
                <time>11:54:11.484+02:00</time>
            </lastMessage>
            <numOfViews>0</numOfViews>
            <numOfResponses>0</numOfResponses>
        </subThreads>
        <subThreads>
            <startMessage>
                <messageID>2</messageID>
                <author>
                    <username>sepetnit</username>
                    <e-mail>fff@ggg</e-mail>
                    <password>uyjzb3Bz</password>
                    <lastName>sepet</lastName>
                    <firstName>vit</firstName>
                    <numOfPostedMessages>3</numOfPostedMessages>
                </author>
                <title>sssss</title>
                <content>ooooooops</content>
                <date>2010-03-15+02:00</date>
                <time>13:25:30.859+02:00</time>
            </startMessage>
            <lastMessage>
                <messageID>2</messageID>
                <author>
                    <username>sepetnit</username>
                    <e-mail>fff@ggg</e-mail>
                    <password>uyjzb3Bz</password>
                    <lastName>sepet</lastName>
                    <firstName>vit</firstName>
                    <numOfPostedMessages>3</numOfPostedMessages>
                </author>
                <title>sssss</title>
                <content>ooooooops</content>
                <date>2010-03-15+02:00</date>
                <time>13:25:30.859+02:00</time>
            </lastMessage>
            <numOfViews>0</numOfViews>
            <numOfResponses>0</numOfResponses>
        </subThreads>
        <subThreads>
            <startMessage>
                <messageID>3</messageID>
                <author>
                    <username>yakir</username>
                    <e-mail>dahany@bgu.ac.il</e-mail>
                    <password>1234</password>
                    <lastName>Dahan</lastName>
                    <firstName>Yakir</firstName>
                    <numOfPostedMessages>1</numOfPostedMessages>
                </author>
                <title>ieee</title>
                <content>wow</content>
                <date>2010-03-15+02:00</date>
                <time>13:30:37.921+02:00</time>
            </startMessage>
            <lastMessage>
                <messageID>3</messageID>
                <author>
                    <username>yakir</username>
                    <e-mail>dahany@bgu.ac.il</e-mail>
                    <password>1234</password>
                    <lastName>Dahan</lastName>
                    <firstName>Yakir</firstName>
                    <numOfPostedMessages>1</numOfPostedMessages>
                </author>
                <title>ieee</title>
                <content>wow</content>
                <date>2010-03-15+02:00</date>
                <time>13:30:37.921+02:00</time>
            </lastMessage>
            <numOfViews>0</numOfViews>
            <numOfResponses>0</numOfResponses>
        </subThreads>
        <numOfThreads>4</numOfThreads>
        <lastAddedMessage>
            <messageID>3</messageID>
            <author>
                <username>yakir</username>
                <e-mail>dahany@bgu.ac.il</e-mail>
                <password>1234</password>
                <lastName>Dahan</lastName>
                <firstName>Yakir</firstName>
                <numOfPostedMessages>1</numOfPostedMessages>
            </author>
            <title>ieee</title>
            <content>wow</content>
            <date>2010-03-15+02:00</date>
            <time>13:30:37.921+02:00</time>
        </lastAddedMessage>
    </forumSubjects>
    <forumSubjects>
        <name>t6</name>
        <description>u7</description>
        <numOfMessages>0</numOfMessages>
        <subjectID>1</subjectID>
        <numOfThreads>0</numOfThreads>
    </forumSubjects>
    <numOfMessages>4</numOfMessages>
</ForumType>
